CoDrone/__init__.py
CoDrone/codrone.py
CoDrone/crc.py
CoDrone/protocol.py
CoDrone/receiver.py
CoDrone/storage.py
CoDrone/system.py
CoDrone-1.2.8.dist-info/METADATA
CoDrone-1.2.8.dist-info/WHEEL
CoDrone-1.2.8.dist-info/top_level.txt
CoDrone-1.2.8.dist-info/RECORD
