Metadata-Version: 2.1
Name: CoDrone
Version: 1.2.8
Summary: Python package for CoDrone
Home-page: https://github.com/RobolinkInc/CoDrone-python.git
Author: Robolink
Author-email: info@robolink.com
License: UNKNOWN
Keywords: robolink,drone,codrone
Platform: UNKNOWN
Requires-Python: >=3
Requires-Dist: pyserial (>=3.5)
Requires-Dist: numpy
Requires-Dist: colorama
Requires-Dist: matplotlib
